{
  "40b8d1": {
    "kind": "farm-test-broadcast",
    "message": "[FARM TEST] Group confirmation request \u2014 reply YES or Y to confirm. I'll let everyone know as confirmations come in.\n\nSample trade: SELL 1,000 bu Nov '26 soybeans @ $10.45 ($10,450). Daily @ Risk \u00b1$430.\n\nRequired: Maryann, Dan, Susan.\nOptional: Patrick, Kevin, Alison.\n\nOne-time test, thanks.",
    "optional": [
      "+16302479950",
      "+17084203265",
      "+17087109385"
    ],
    "pulses": {},
    "recipients": {
      "+13126361666": {
        "last_reminded_at": "2026-05-01T16:30:56.520961+00:00",
        "name": "Dan Cooke",
        "raw": "Y",
        "reminders_sent": 4,
        "replied_at": "2026-05-01T16:43:13.320Z",
        "send_ok": true,
        "vote": "Y"
      },
      "+16302122546": {
        "name": "Maryann Meyer",
        "raw": "Y",
        "replied_at": "2026-05-01T14:41:00.618Z",
        "send_ok": true,
        "vote": "Y"
      },
      "+16302479950": {
        "name": "Patrick Meyer",
        "raw": "Y",
        "replied_at": "2026-05-01T14:37:57.375Z",
        "send_ok": true,
        "vote": "Y"
      },
      "+17084203265": {
        "last_reminded_at": "2026-05-01T16:30:56.520961+00:00",
        "name": "Kevin Cooke",
        "raw": "Y",
        "reminders_sent": 4,
        "replied_at": "2026-05-01T16:49:04.458Z",
        "send_ok": true,
        "vote": "Y"
      },
      "+17087109385": {
        "name": "Alison Lindeen",
        "raw": "Y",
        "replied_at": "2026-05-01T14:49:26.572Z",
        "send_ok": true,
        "vote": "Y"
      },
      "+17087109387": {
        "last_reminded_at": "2026-05-01T15:07:36.129422+00:00",
        "name": "Sue Lindeen",
        "raw": "Y",
        "reminders_sent": 1,
        "replied_at": "2026-05-01T15:13:46.704Z",
        "send_ok": true,
        "vote": "Y"
      }
    },
    "required": [
      "+16302122546",
      "+13126361666",
      "+17087109387"
    ],
    "sent_at": "2026-05-01T14:37:12.183447+00:00",
    "signal_key": "farm-test|group-confirmation|2026-05-01T14:37:12",
    "status": "confirmed"
  },
  "46061e": {
    "message": "FREIS FARM confirmation test \u2014 this is a drill, not a real signal. Reply 'Y 46061e' to confirm, 'N 46061e' to veto.",
    "recipients": {
      "+16302479950": {
        "raw": "Y 46061e",
        "replied_at": "2026-04-22T04:05:34.984Z",
        "vote": "Y"
      }
    },
    "sent_at": "2026-04-22T04:03:14.657736+00:00",
    "signal_key": "test|2026-04-22T04-03-14|CONFIRM",
    "status": "confirmed"
  },
  "7208d2": {
    "message": "CORN: Sell 8,250 @ $4.75 ($39,188). 1d risk -$1,620. Reply Y or N.",
    "recipients": {
      "+16302122546": {
        "last_reminded_at": "2026-05-01T13:36:28.393881+00:00",
        "raw": "Y",
        "reminders_sent": 1,
        "replied_at": "2026-05-01T13:46:40.473Z",
        "vote": "Y"
      },
      "+16302479950": {
        "raw": "Y",
        "replied_at": "2026-04-30T22:51:31.582Z",
        "vote": "Y"
      }
    },
    "sent_at": "2026-04-30T22:51:05.914462+00:00",
    "signal_key": "sim|corn|Dec '26|SELL|4.7400|2026-04-30T22:51:05",
    "status": "confirmed"
  },
  "7587d1": {
    "kind": "farm-test-broadcast-solo",
    "message": "[FARM TEST] Group confirmation request \u2014 reply YES or Y to confirm. I'll let everyone know as confirmations come in.\n\nSample trade: SELL 1,000 bu Nov '26 soybeans @ $10.45 ($10,450). Daily @ Risk \u00b1$430.\n\nRequired: Maryann, Dan, Susan.\nOptional: Patrick, Kevin, Alison.\n\nOne-time test, thanks.",
    "optional": [
      "+16302479950"
    ],
    "pulses": {},
    "recipients": {
      "+16302479950": {
        "last_reminded_at": "2026-05-01T16:02:54.121667+00:00",
        "name": "Patrick Meyer (solo)",
        "raw": "Y",
        "reminders_sent": 4,
        "replied_at": "2026-05-01T16:04:42.754Z",
        "send_ok": true,
        "vote": "Y"
      }
    },
    "required": [],
    "sent_at": "2026-05-01T14:20:42.618588+00:00",
    "signal_key": "solo|farm-test|group-confirmation|2026-05-01T14:20:42",
    "status": "confirmed"
  },
  "_orphans": [
    {
      "phone": "+16302479950",
      "received_at": "2026-04-22T04:03:58.955Z",
      "short_id": "460616",
      "text": "Y 460616",
      "vote": "Y"
    },
    {
      "phone": "+16302479950",
      "received_at": "2026-05-01T13:40:31.564Z",
      "text": "Y",
      "vote": "Y"
    },
    {
      "phone": "+16302479950",
      "received_at": "2026-05-04T16:35:02.022Z",
      "text": "Y",
      "vote": "Y"
    },
    {
      "phone": "+17087109387",
      "received_at": "2026-05-04T16:40:11.025Z",
      "text": "Y",
      "vote": "Y"
    }
  ],
  "b6a7a1": {
    "kind": "farm-test-broadcast-solo",
    "message": "[FARM TEST] Group confirmation request \u2014 reply YES or Y to confirm. I'll let everyone know as confirmations come in.\n\nSample trade: SELL 1,000 bu Nov '26 soybeans @ $10.45 ($10,450). Daily @ Risk \u00b1$430.\n\nRequired: Maryann, Dan, Susan.\nOptional: Patrick, Kevin, Alison.\n\nOne-time test, thanks.",
    "optional": [
      "+16302479950"
    ],
    "recipients": {
      "+16302479950": {
        "name": "Patrick Meyer (solo)",
        "raw": "YES",
        "replied_at": "2026-05-01T14:40:38.535Z",
        "send_ok": true,
        "vote": "Y"
      }
    },
    "required": [],
    "sent_at": "2026-05-01T14:35:55.990502+00:00",
    "signal_key": "solo|farm-test|group-confirmation|2026-05-01T14:35:55",
    "status": "confirmed"
  },
  "e8e5c9": {
    "message": "CORN: Sell 8,250 @ $4.75 ($39,188). 1d risk -$1,620. Reply Y or N.",
    "recipients": {
      "+16302479950": {
        "last_reminded_at": "2026-04-30T19:36:46.403470+00:00",
        "raw": "Y",
        "reminders_sent": 1,
        "replied_at": "2026-04-30T19:37:18.619Z",
        "vote": "Y"
      }
    },
    "sent_at": "2026-04-30T19:04:25.025355+00:00",
    "signal_key": "sim|corn|Dec '26|SELL|4.7400|2026-04-30T19:04:25",
    "status": "confirmed"
  },
  "smoke1": {
    "message": "FREIS FARM reminder-system smoke test (round 2)",
    "recipients": {
      "+16302479950": {
        "last_reminded_at": "2026-04-23T13:40:15.020222+00:00",
        "raw": "Y",
        "reminders_sent": 3,
        "replied_at": "2026-04-23T13:42:39.613Z",
        "vote": "Y"
      }
    },
    "sent_at": "2026-04-22T18:00:40.698865+00:00",
    "signal_key": "test|reminder-smoketest",
    "status": "confirmed"
  }
}
